{
    "data": [
        {
            "traceID": "0444fbf74fffc318",
            "spans": [
                {
                    "traceID": "0444fbf74fffc318",
                    "spanID": "8ee905d0e1c4df72",
                    "flags": 1,
                    "operationName": "/wrk2-api/post/compose",
                    "references": [
                        {
                            "refType": "CHILD_OF",
                            "traceID": "0444fbf74fffc318",
                            "spanID": "0444fbf74fffc318"
                        }
                    ],
                    "startTime": 1711340414442830,
                    "duration": 201769,
                    "tags": [
                        {
                            "key": "component",
                            "type": "string",
                            "value": "nginx"
                        },
                        {
                            "key": "nginx.worker_pid",
                            "type": "string",
                            "value": "12"
                        },
                        {
                            "key": "peer.address",
                            "type": "string",
                            "value": "10.0.0.2:57784"
                        },
                        {
                            "key": "http.method",
                            "type": "string",
                            "value": "POST"
                        },
                        {
                            "key": "http.url",
                            "type": "string",
                            "value": "http://127.0.0.1:8080/wrk2-api/post/compose"
                        },
                        {
                            "key": "http.host",
                            "type": "string",
                            "value": "127.0.0.1:8080"
                        },
                        {
                            "key": "http.status_code",
                            "type": "int64",
                            "value": 200
                        },
                        {
                            "key": "http.status_line",
                            "type": "string",
                            "value": ""
                        },
                        {
                            "key": "internal.span.format",
                            "type": "string",
                            "value": "proto"
                        }
                    ],
                    "logs": [],
                    "processID": "p1",
                    "warnings": null
                },
                {
                    "traceID": "0444fbf74fffc318",
                    "spanID": "0444fbf74fffc318",
                    "flags": 1,
                    "operationName": "/wrk2-api/post/compose",
                    "references": [],
                    "startTime": 1711340414442000,
                    "duration": 202600,
                    "tags": [
                        {
                            "key": "sampler.type",
                            "type": "string",
                            "value": "probabilistic"
                        },
                        {
                            "key": "sampler.param",
                            "type": "float64",
                            "value": 0.2
                        },
                        {
                            "key": "http.status_code",
                            "type": "int64",
                            "value": 200
                        },
                        {
                            "key": "http.status_line",
                            "type": "string",
                            "value": ""
                        },
                        {
                            "key": "component",
                            "type": "string",
                            "value": "nginx"
                        },
                        {
                            "key": "nginx.worker_pid",
                            "type": "string",
                            "value": "12"
                        },
                        {
                            "key": "peer.address",
                            "type": "string",
                            "value": "10.0.0.2:57784"
                        },
                        {
                            "key": "http.method",
                            "type": "string",
                            "value": "POST"
                        },
                        {
                            "key": "http.url",
                            "type": "string",
                            "value": "http://127.0.0.1:8080/wrk2-api/post/compose"
                        },
                        {
                            "key": "http.host",
                            "type": "string",
                            "value": "127.0.0.1:8080"
                        },
                        {
                            "key": "internal.span.format",
                            "type": "string",
                            "value": "proto"
                        }
                    ],
                    "logs": [],
                    "processID": "p1",
                    "warnings": null
                },
                {
                    "traceID": "0444fbf74fffc318",
                    "spanID": "e2e7cf03e1fad96e",
                    "flags": 1,
                    "operationName": "compose_media_server",
                    "references": [
                        {
                            "refType": "CHILD_OF",
                            "traceID": "0444fbf74fffc318",
                            "spanID": "16d84fad57dc2d3c"
                        }
                    ],
                    "startTime": 1711340414523455,
                    "duration": 13,
                    "tags": [
                        {
                            "key": "internal.span.format",
                            "type": "string",
                            "value": "proto"
                        }
                    ],
                    "logs": [],
                    "processID": "p4",
                    "warnings": [
                        "invalid parent span IDs=16d84fad57dc2d3c; skipping clock skew adjustment"
                    ]
                },
                {
                    "traceID": "0444fbf74fffc318",
                    "spanID": "31df6bd6f0768ddb",
                    "flags": 1,
                    "operationName": "compose_post_client",
                    "references": [
                        {
                            "refType": "CHILD_OF",
                            "traceID": "0444fbf74fffc318",
                            "spanID": "8ee905d0e1c4df72"
                        }
                    ],
                    "startTime": 1711340414442947,
                    "duration": 201581,
                    "tags": [
                        {
                            "key": "internal.span.format",
                            "type": "string",
                            "value": "proto"
                        }
                    ],
                    "logs": [],
                    "processID": "p1",
                    "warnings": null
                },
                {
                    "traceID": "0444fbf74fffc318",
                    "spanID": "0b633748b70a7612",
                    "flags": 1,
                    "operationName": "compose_text_server",
                    "references": [
                        {
                            "refType": "CHILD_OF",
                            "traceID": "0444fbf74fffc318",
                            "spanID": "e123642dca2b282e"
                        }
                    ],
                    "startTime": 1711340414509052,
                    "duration": 2507,
                    "tags": [
                        {
                            "key": "internal.span.format",
                            "type": "string",
                            "value": "proto"
                        }
                    ],
                    "logs": [],
                    "processID": "p2",
                    "warnings": [
                        "invalid parent span IDs=e123642dca2b282e; skipping clock skew adjustment"
                    ]
                },
                {
                    "traceID": "0444fbf74fffc318",
                    "spanID": "0f5be9f9d22a3de2",
                    "flags": 1,
                    "operationName": "compose_unique_id_server",
                    "references": [
                        {
                            "refType": "CHILD_OF",
                            "traceID": "0444fbf74fffc318",
                            "spanID": "08f6bfe1a6d3e69a"
                        }
                    ],
                    "startTime": 1711340414524148,
                    "duration": 19,
                    "tags": [
                        {
                            "key": "internal.span.format",
                            "type": "string",
                            "value": "proto"
                        }
                    ],
                    "logs": [],
                    "processID": "p9",
                    "warnings": [
                        "invalid parent span IDs=08f6bfe1a6d3e69a; skipping clock skew adjustment"
                    ]
                },
                {
                    "traceID": "0444fbf74fffc318",
                    "spanID": "5b7ceff088012a2f",
                    "flags": 1,
                    "operationName": "compose_urls_client",
                    "references": [
                        {
                            "refType": "CHILD_OF",
                            "traceID": "0444fbf74fffc318",
                            "spanID": "0b633748b70a7612"
                        }
                    ],
                    "startTime": 1711340414509417,
                    "duration": 1289,
                    "tags": [
                        {
                            "key": "internal.span.format",
                            "type": "string",
                            "value": "proto"
                        }
                    ],
                    "logs": [],
                    "processID": "p2",
                    "warnings": null
                },
                {
                    "traceID": "0444fbf74fffc318",
                    "spanID": "a6cf1eec96a5c75b",
                    "flags": 1,
                    "operationName": "compose_urls_server",
                    "references": [
                        {
                            "refType": "CHILD_OF",
                            "traceID": "0444fbf74fffc318",
                            "spanID": "5b7ceff088012a2f"
                        }
                    ],
                    "startTime": 1711340414507909,
                    "duration": 874,
                    "tags": [
                        {
                            "key": "internal.span.format",
                            "type": "string",
                            "value": "proto"
                        }
                    ],
                    "logs": [],
                    "processID": "p3",
                    "warnings": null
                },
                {
                    "traceID": "0444fbf74fffc318",
                    "spanID": "9779bba8772a21da",
                    "flags": 1,
                    "operationName": "compose_user_mentions_client",
                    "references": [
                        {
                            "refType": "CHILD_OF",
                            "traceID": "0444fbf74fffc318",
                            "spanID": "0b633748b70a7612"
                        }
                    ],
                    "startTime": 1711340414509490,
                    "duration": 1871,
                    "tags": [
                        {
                            "key": "internal.span.format",
                            "type": "string",
                            "value": "proto"
                        }
                    ],
                    "logs": [],
                    "processID": "p2",
                    "warnings": null
                },
                {
                    "traceID": "0444fbf74fffc318",
                    "spanID": "ede652035863775b",
                    "flags": 1,
                    "operationName": "compose_user_mentions_memcached_get_client",
                    "references": [
                        {
                            "refType": "CHILD_OF",
                            "traceID": "0444fbf74fffc318",
                            "spanID": "1a1017fce5a311e3"
                        }
                    ],
                    "startTime": 1711340414509521,
                    "duration": 1010,
                    "tags": [
                        {
                            "key": "internal.span.format",
                            "type": "string",
                            "value": "proto"
                        }
                    ],
                    "logs": [],
                    "processID": "p5",
                    "warnings": null
                },
                {
                    "traceID": "0444fbf74fffc318",
                    "spanID": "20fa293f714857e2",
                    "flags": 1,
                    "operationName": "compose_user_mentions_mongo_find_client",
                    "references": [
                        {
                            "refType": "CHILD_OF",
                            "traceID": "0444fbf74fffc318",
                            "spanID": "1a1017fce5a311e3"
                        }
                    ],
                    "startTime": 1711340414510553,
                    "duration": 390,
                    "tags": [
                        {
                            "key": "internal.span.format",
                            "type": "string",
                            "value": "proto"
                        }
                    ],
                    "logs": [],
                    "processID": "p5",
                    "warnings": null
                },
                {
                    "traceID": "0444fbf74fffc318",
                    "spanID": "1a1017fce5a311e3",
                    "flags": 1,
                    "operationName": "compose_user_mentions_server",
                    "references": [
                        {
                            "refType": "CHILD_OF",
                            "traceID": "0444fbf74fffc318",
                            "spanID": "9779bba8772a21da"
                        }
                    ],
                    "startTime": 1711340414509507,
                    "duration": 1448,
                    "tags": [
                        {
                            "key": "internal.span.format",
                            "type": "string",
                            "value": "proto"
                        }
                    ],
                    "logs": [],
                    "processID": "p5",
                    "warnings": null
                },
                {
                    "traceID": "0444fbf74fffc318",
                    "spanID": "0d10ac924c19447d",
                    "flags": 1,
                    "operationName": "get_followers_client",
                    "references": [
                        {
                            "refType": "CHILD_OF",
                            "traceID": "0444fbf74fffc318",
                            "spanID": "289ca90d02f90325"
                        }
                    ],
                    "startTime": 1711340414599064,
                    "duration": 1692,
                    "tags": [
                        {
                            "key": "internal.span.format",
                            "type": "string",
                            "value": "proto"
                        }
                    ],
                    "logs": [],
                    "processID": "p8",
                    "warnings": null
                },
                {
                    "traceID": "0444fbf74fffc318",
                    "spanID": "5c671ee1396f0050",
                    "flags": 1,
                    "operationName": "get_followers_server",
                    "references": [
                        {
                            "refType": "CHILD_OF",
                            "traceID": "0444fbf74fffc318",
                            "spanID": "0d10ac924c19447d"
                        }
                    ],
                    "startTime": 1711340414600264,
                    "duration": 1118,
                    "tags": [
                        {
                            "key": "internal.span.format",
                            "type": "string",
                            "value": "proto"
                        }
                    ],
                    "logs": [],
                    "processID": "p7",
                    "warnings": null
                },
                {
                    "traceID": "0444fbf74fffc318",
                    "spanID": "7c3d1bd17c01c804",
                    "flags": 1,
                    "operationName": "post_storage_mongo_insert_client",
                    "references": [
                        {
                            "refType": "CHILD_OF",
                            "traceID": "0444fbf74fffc318",
                            "spanID": "f18030f266f451b6"
                        }
                    ],
                    "startTime": 1711340414571788,
                    "duration": 824,
                    "tags": [
                        {
                            "key": "internal.span.format",
                            "type": "string",
                            "value": "proto"
                        }
                    ],
                    "logs": [],
                    "processID": "p6",
                    "warnings": null
                },
                {
                    "traceID": "0444fbf74fffc318",
                    "spanID": "f4408213176702b1",
                    "flags": 1,
                    "operationName": "social_graph_mongo_find_client",
                    "references": [
                        {
                            "refType": "CHILD_OF",
                            "traceID": "0444fbf74fffc318",
                            "spanID": "5c671ee1396f0050"
                        }
                    ],
                    "startTime": 1711340414600651,
                    "duration": 715,
                    "tags": [
                        {
                            "key": "internal.span.format",
                            "type": "string",
                            "value": "proto"
                        }
                    ],
                    "logs": [],
                    "processID": "p7",
                    "warnings": null
                },
                {
                    "traceID": "0444fbf74fffc318",
                    "spanID": "46590a8bf6cea82b",
                    "flags": 1,
                    "operationName": "social_graph_redis_get_client",
                    "references": [
                        {
                            "refType": "CHILD_OF",
                            "traceID": "0444fbf74fffc318",
                            "spanID": "5c671ee1396f0050"
                        }
                    ],
                    "startTime": 1711340414600276,
                    "duration": 345,
                    "tags": [
                        {
                            "key": "internal.span.format",
                            "type": "string",
                            "value": "proto"
                        }
                    ],
                    "logs": [],
                    "processID": "p7",
                    "warnings": null
                },
                {
                    "traceID": "0444fbf74fffc318",
                    "spanID": "f18030f266f451b6",
                    "flags": 1,
                    "operationName": "store_post_server",
                    "references": [
                        {
                            "refType": "CHILD_OF",
                            "traceID": "0444fbf74fffc318",
                            "spanID": "882c04b0661a4a25"
                        }
                    ],
                    "startTime": 1711340414571762,
                    "duration": 893,
                    "tags": [
                        {
                            "key": "internal.span.format",
                            "type": "string",
                            "value": "proto"
                        }
                    ],
                    "logs": [],
                    "processID": "p6",
                    "warnings": [
                        "invalid parent span IDs=882c04b0661a4a25; skipping clock skew adjustment"
                    ]
                },
                {
                    "traceID": "0444fbf74fffc318",
                    "spanID": "54897910d39bf240",
                    "flags": 1,
                    "operationName": "url_mongo_insert_client",
                    "references": [
                        {
                            "refType": "CHILD_OF",
                            "traceID": "0444fbf74fffc318",
                            "spanID": "a6cf1eec96a5c75b"
                        }
                    ],
                    "startTime": 1711340414508053,
                    "duration": 683,
                    "tags": [
                        {
                            "key": "internal.span.format",
                            "type": "string",
                            "value": "proto"
                        }
                    ],
                    "logs": [],
                    "processID": "p3",
                    "warnings": null
                },
                {
                    "traceID": "0444fbf74fffc318",
                    "spanID": "f5c9e3d1fb3148b0",
                    "flags": 1,
                    "operationName": "write_home_timeline_redis_update_client",
                    "references": [
                        {
                            "refType": "CHILD_OF",
                            "traceID": "0444fbf74fffc318",
                            "spanID": "289ca90d02f90325"
                        }
                    ],
                    "startTime": 1711340414600770,
                    "duration": 12,
                    "tags": [
                        {
                            "key": "internal.span.format",
                            "type": "string",
                            "value": "proto"
                        }
                    ],
                    "logs": [],
                    "processID": "p8",
                    "warnings": null
                },
                {
                    "traceID": "0444fbf74fffc318",
                    "spanID": "289ca90d02f90325",
                    "flags": 1,
                    "operationName": "write_home_timeline_server",
                    "references": [
                        {
                            "refType": "CHILD_OF",
                            "traceID": "0444fbf74fffc318",
                            "spanID": "1238e6873f7a5911"
                        }
                    ],
                    "startTime": 1711340414599060,
                    "duration": 1769,
                    "tags": [
                        {
                            "key": "internal.span.format",
                            "type": "string",
                            "value": "proto"
                        }
                    ],
                    "logs": [],
                    "processID": "p8",
                    "warnings": [
                        "invalid parent span IDs=1238e6873f7a5911; skipping clock skew adjustment"
                    ]
                }
            ],
            "processes": {
                "p1": {
                    "serviceName": "nginx-web-server",
                    "tags": [
                        {
                            "key": "hostname",
                            "type": "string",
                            "value": "nginx-web-server"
                        },
                        {
                            "key": "ip",
                            "type": "string",
                            "value": "127.0.0.1"
                        },
                        {
                            "key": "jaeger.version",
                            "type": "string",
                            "value": "C++-0.4.2"
                        }
                    ]
                },
                "p2": {
                    "serviceName": "text-service",
                    "tags": [
                        {
                            "key": "hostname",
                            "type": "string",
                            "value": "text-service"
                        },
                        {
                            "key": "ip",
                            "type": "string",
                            "value": "127.0.0.1"
                        },
                        {
                            "key": "jaeger.version",
                            "type": "string",
                            "value": "C++-0.4.2"
                        }
                    ]
                },
                "p3": {
                    "serviceName": "url-shorten-service",
                    "tags": [
                        {
                            "key": "hostname",
                            "type": "string",
                            "value": "url-shorten-service"
                        },
                        {
                            "key": "ip",
                            "type": "string",
                            "value": "127.0.0.1"
                        },
                        {
                            "key": "jaeger.version",
                            "type": "string",
                            "value": "C++-0.4.2"
                        }
                    ]
                },
                "p4": {
                    "serviceName": "media-service",
                    "tags": [
                        {
                            "key": "hostname",
                            "type": "string",
                            "value": "media-service"
                        },
                        {
                            "key": "ip",
                            "type": "string",
                            "value": "127.0.0.1"
                        },
                        {
                            "key": "jaeger.version",
                            "type": "string",
                            "value": "C++-0.4.2"
                        }
                    ]
                },
                "p5": {
                    "serviceName": "user-mention-service",
                    "tags": [
                        {
                            "key": "hostname",
                            "type": "string",
                            "value": "user-mention-service"
                        },
                        {
                            "key": "ip",
                            "type": "string",
                            "value": "127.0.0.1"
                        },
                        {
                            "key": "jaeger.version",
                            "type": "string",
                            "value": "C++-0.4.2"
                        }
                    ]
                },
                "p6": {
                    "serviceName": "post-storage-service",
                    "tags": [
                        {
                            "key": "hostname",
                            "type": "string",
                            "value": "post-storage-service"
                        },
                        {
                            "key": "ip",
                            "type": "string",
                            "value": "127.0.0.1"
                        },
                        {
                            "key": "jaeger.version",
                            "type": "string",
                            "value": "C++-0.4.2"
                        }
                    ]
                },
                "p7": {
                    "serviceName": "social-graph-service",
                    "tags": [
                        {
                            "key": "hostname",
                            "type": "string",
                            "value": "social-graph-service"
                        },
                        {
                            "key": "ip",
                            "type": "string",
                            "value": "127.0.0.1"
                        },
                        {
                            "key": "jaeger.version",
                            "type": "string",
                            "value": "C++-0.4.2"
                        }
                    ]
                },
                "p8": {
                    "serviceName": "home-timeline-service",
                    "tags": [
                        {
                            "key": "hostname",
                            "type": "string",
                            "value": "home-timeline-service"
                        },
                        {
                            "key": "ip",
                            "type": "string",
                            "value": "127.0.0.1"
                        },
                        {
                            "key": "jaeger.version",
                            "type": "string",
                            "value": "C++-0.4.2"
                        }
                    ]
                },
                "p9": {
                    "serviceName": "unique-id-service",
                    "tags": [
                        {
                            "key": "hostname",
                            "type": "string",
                            "value": "unique-id-service"
                        },
                        {
                            "key": "ip",
                            "type": "string",
                            "value": "127.0.0.1"
                        },
                        {
                            "key": "jaeger.version",
                            "type": "string",
                            "value": "C++-0.4.2"
                        }
                    ]
                }
            },
            "warnings": null
        }
    ],
    "total": 0,
    "limit": 0,
    "offset": 0,
    "errors": null
}